asociita/__init__.py
asociita/components/archiver/archive_manager.py
asociita/components/evaluator/evaluation_manager.py
asociita/components/evaluator/lsaa_evaluator.py
asociita/components/evaluator/mr_evaluator.py
asociita/components/evaluator/or_evaluator.py
asociita/components/evaluator/sample_evaluator.py
asociita/components/nodes/federated_node.py
asociita/components/orchestrator/evaluator_orchestrator.py
asociita/components/orchestrator/fedopt_orchestrator.py
asociita/components/orchestrator/generic_orchestrator.py
asociita/components/settings/evaluator_settings.py
asociita/components/settings/fedopt_settings.py
asociita/components/settings/init_settings.py
asociita/components/settings/settings.py
asociita/datasets/fetch_data.py
asociita/datasets/load_cifar.py
asociita/datasets/load_fmnist.py
asociita/datasets/load_mnist.py
asociita/datasets/save_blueprint.py
asociita/datasets/shard_splits.py
asociita/datasets/shard_transformation.py
asociita/exceptions/evaluatorexception.py
asociita/exceptions/modelexception.py
asociita/exceptions/settingexception.py
asociita/models/pytorch/cifar10.py
asociita/models/pytorch/federated_model.py
asociita/models/pytorch/fmnist.py
asociita/models/pytorch/mnist.py
asociita/utils/computations.py
asociita/utils/custom_transformations.py
asociita/utils/debugger.py
asociita/utils/handlers.py
asociita/utils/helpers.py
asociita/utils/loggers.py
asociita/utils/optimizers.py
asociita/utils/orchestrations.py
asociita/utils/showcase.py
asociita-0.3.4.dist-info/LICENSE
asociita-0.3.4.dist-info/METADATA
asociita-0.3.4.dist-info/WHEEL
asociita-0.3.4.dist-info/RECORD
